pdflex/__init__.py
pdflex/cli.py
pdflex/exceptions.py
pdflex/logger.py
pdflex/merge.py
pdflex/pdf_to_txt.py
pdflex/search.py
pdflex-0.1.9.dist-info/METADATA
pdflex-0.1.9.dist-info/WHEEL
pdflex-0.1.9.dist-info/entry_points.txt
pdflex-0.1.9.dist-info/licenses/LICENSE
pdflex-0.1.9.dist-info/RECORD
