Metadata-Version: 2.4
Name: pdflex
Version: 0.1.9
Summary: Python tools for PDF automation.
Project-URL: Homepage, https://github.com/eli64s/pdflex
Author-email: Eli Salamie <egsalamie@gmail.com>
License-Expression: MIT
License-File: LICENSE
Keywords: pdf-automation,pdf-converter,pdf-data-extraction,pdf-document,pdf-document-parser,pdf-document-processor,pdf-extractor,pdf-generator,pdf-library,pdf-manipulation,pdf-parser,pdf-processor,pdf-python,pdf-reader,pdf-regex,pdf-search,pdf-text-extraction,pdf-tools,python-pdf,python-pdf-tools
Classifier: Development Status :: 4 - Beta
Classifier: Environment :: Console
Classifier: Framework :: Pytest
Classifier: Intended Audience :: Developers
Classifier: Intended Audience :: Financial and Insurance Industry
Classifier: Intended Audience :: Information Technology
Classifier: Intended Audience :: Legal Industry
Classifier: License :: OSI Approved :: MIT License
Classifier: Natural Language :: English
Classifier: Operating System :: MacOS
Classifier: Operating System :: Microsoft :: Windows
Classifier: Operating System :: OS Independent
Classifier: Operating System :: POSIX :: Linux
Classifier: Programming Language :: Python :: 3 :: Only
Classifier: Programming Language :: Python :: 3.9
Classifier: Programming Language :: Python :: 3.10
Classifier: Programming Language :: Python :: 3.11
Classifier: Programming Language :: Python :: 3.12
Classifier: Programming Language :: Python :: 3.13
Classifier: Topic :: Documentation
Classifier: Topic :: Office/Business
Classifier: Topic :: Printing
Classifier: Topic :: Scientific/Engineering :: Image Processing
Classifier: Topic :: Software Development :: Libraries :: Python Modules
Classifier: Topic :: Text Processing :: Filters
Classifier: Topic :: Text Processing :: General
Classifier: Topic :: Text Processing :: Indexing
Classifier: Typing :: Typed
Requires-Python: <=3.14,>=3.9
Requires-Dist: pdfplumber>=0.11.5
Requires-Dist: pydantic
Requires-Dist: pydantic-settings
Requires-Dist: pymupdf
Requires-Dist: pypdf
Requires-Dist: reportlab
Requires-Dist: rich
